flexsolve/__init__.py
flexsolve/bounded_solvers.py
flexsolve/iterative_solvers.py
flexsolve/open_solvers.py
flexsolve/problem.py
flexsolve/problem_list.py
flexsolve/profiler.py
flexsolve/utils.py
flexsolve-0.5.4.dist-info/LICENSE.txt
flexsolve-0.5.4.dist-info/METADATA
flexsolve-0.5.4.dist-info/WHEEL
flexsolve-0.5.4.dist-info/top_level.txt
flexsolve-0.5.4.dist-info/RECORD
