Metadata-Version: 2.1
Name: flexsolve
Version: 0.5.4
Summary: Flexible function solvers
Home-page: https://github.com/yoelcortes/flexsolve
Download-URL: https://github.com/yoelcortes/flexsolve.git
Author: Yoel Cortes-Pena
Author-email: yoelcortes@gmail.com
License: MIT
Keywords: solve,equation,function,flexible
Platform: Windows
Platform: Mac
Platform: Linux
Classifier: Development Status :: 3 - Alpha
Classifier: Environment :: Console
Classifier: License :: OSI Approved :: MIT License
Classifier: Topic :: Education
Classifier: Topic :: Scientific/Engineering
Classifier: Topic :: Scientific/Engineering :: Mathematics
Classifier: Intended Audience :: Developers
Classifier: Intended Audience :: Education
Classifier: Intended Audience :: Manufacturing
Classifier: Intended Audience :: Science/Research
Classifier: Natural Language :: English
Classifier: Operating System :: MacOS
Classifier: Operating System :: Microsoft :: Windows
Classifier: Operating System :: POSIX
Classifier: Operating System :: POSIX :: BSD
Classifier: Operating System :: POSIX :: Linux
Classifier: Operating System :: Unix
Classifier: Programming Language :: Python :: 3.6
Classifier: Programming Language :: Python :: 3.7
Classifier: Programming Language :: Python :: 3.8
Classifier: Programming Language :: Python :: Implementation :: CPython
Requires-Python: >=3.6
License-File: LICENSE.txt
Requires-Dist: numba (>=0.50.0)
Requires-Dist: llvmlite (>=0.31)
Requires-Dist: numpy
